{
	"pages": [ //pages数组中第一项表示应用启动页，参考：https://uniapp.dcloud.io/collocation/pages
		{
			"path": "pages/index/index",
			"style": {
				"navigationBarTitleText": "首页"
			}
		},
		{
		  "path" : "pages/index/components/Banner/Banner",
		  "style" : 
		  {
		    "navigationBarTitleText" : ""
		  }
		},
		{
		  "path" : "pages/mine/mine",
		  "style" : 
		  {
		    "navigationBarTitleText" : "个人主页"
		  }
		},
		{
		  "path" : "pages/index/components/Menu/components/dayNew",
		  "name": "dayNew",
		  "style" : 
		  {
		    "navigationBarTitleText" : "每日推荐"
		  }
		},
		{
		  "path" : "pages/index/components/Menu/components/rank",
		  "name": "pages/index/components/Menu/components/rank",
		  "style" : 
		  {
		    "navigationBarTitleText" : "排行榜",
			"navigationBarBackgroundColor":"#f80e41",
			"navigationBarTextStyle":"white"
			
		  }
		}
	],
	"globalStyle": {
		"navigationBarTextStyle": "black",
		"navigationBarTitleText": "uni-app",
		"navigationBarBackgroundColor": "#F8F8F8",
		"backgroundColor": "#F8F8F8"
	},
  "tabBar": {
    "list": [
      {
        "pagePath": "pages/index/index",
        "text": "发现",
        "iconfont": {
          "text": "\ue102",
          "selectedText": "\ue103",
          "fontSize": "17px",
          "color": "#000000",
          "selectedColor": "#0000ff"
        }
      },
      {
        "pagePath": "pages/mine/mine",
        "text": "我的",
        "iconfont": {
          "text": "\ue102",
          "selectedText": "\ue103",
          "fontSize": "17px",
          "color": "#000000",
          "selectedColor": "#0000ff"
        }
      }
    ]
  },
	"uniIdRouter": {}
}
